{ "height":8,
 "layers":[
        {
         "data":[3, 3, 3, 3, 3, 3, 3, 3, 3, 3, 3, 3, 3, 2, 2, 2, 2, 2, 2, 2, 2, 2, 2, 3, 3, 2, 2, 3, 3, 2, 2, 2, 3, 2, 2, 3, 3, 2, 2, 3, 2, 2, 2, 2, 3, 2, 2, 3, 3, 2, 2, 2, 2, 2, 2, 3, 2, 2, 2, 3, 3, 2, 3, 2, 2, 2, 2, 2, 2, 2, 2, 3, 3, 2, 2, 2, 2, 2, 2, 2, 2, 2, 2, 3, 3, 3, 3, 3, 3, 3, 3, 3, 3, 3, 3, 3],
         "height":8,
         "name":"Tile Layer 1",
         "opacity":1,
         "type":"tilelayer",
         "visible":true,
         "width":12,
         "x":0,
         "y":0
        }],
 "nextobjectid":1,
 "orientation":"orthogonal",
 "renderorder":"right-down",
 "tileheight":64,
 "tilesets":[
        {
         "columns":5,
         "firstgid":1,
         "image":"SpriteSheet.png",
         "imageheight":64,
         "imagewidth":320,
         "margin":0,
         "name":"SpriteSheet",
         "spacing":0,
         "tilecount":5,
         "tileheight":64,
         "tilewidth":64
        }],
 "tilewidth":64,
 "version":1,
 "width":12
}